LICENSE.txt
README.md
setup.cfg
setup.py
gmi_okx.egg-info/PKG-INFO
gmi_okx.egg-info/SOURCES.txt
gmi_okx.egg-info/dependency_links.txt
gmi_okx.egg-info/requires.txt
gmi_okx.egg-info/top_level.txt
okx/__init__.py
okx/client.py
okx/types.py