Metadata-Version: 2.1
Name: gmi-okx
Version: 0.1.13
Summary: Interface to interact with OKX by GetMoney Inc.
Home-page: https://github.com/get-money-inc/okx-py
Author: GetMoney Inc.
Author-email: get.money.inc.official@gmail.com
License: UNKNOWN
Platform: UNKNOWN
Requires-Python: >=3.11
License-File: LICENSE.txt
